Exercises/Minority/Minority.sv


module Minority(
    input logic a, b, c,
    output logic s
);
    logic x, y, z;
    assign x = (~a) & (~b);
    assign y = (~a) & (~c);
    assign z = (~b) & (~c);

    assign s = x | y | z;
endmodule;

Exercises/Minority/Minority_tb.sv
`timescale 1ns/1ns

module Minority_tb;
    logic a;
    logic b;
    logic c;
    logic s;

    Minority dut(a, b, c, s);

    initial begin
        $dumpfile("Minority.vcd");
        $dumpvars(0, Minority_tb);

        a = 0; b = 0; c = 0;
        #1; 
        assert(s == 1) else $error("000 failed"); #1;

        a = 0; b = 0; c = 1;
        #1;
        assert(s == 1) else $error("001 failed"); #1;

        a = 0; b = 1; c = 0;
        #1;
        assert(s == 1) else $error("010 failed"); #1;

        a = 0; b = 1; c = 1;
        #1;
        assert(s == 0) else $error("011 failed"); #1;

        a = 1; b = 0; c = 0;
        #1;
        assert(s == 1) else $error("100 failed"); #1;

        a = 1; b = 0; c = 1;
        #1;
        assert(s == 0) else $error("101 failed"); #1;

        a = 1; b = 1; c = 0;
        #1;
        assert(s == 0) else $error("110 failed"); #1;

        a = 1; b = 1; c = 1;
        #1;
        assert(s == 0) else $error("111 failed"); #1;

        $finish;
    end

endmodule;

Exercises/Minority/Minority.vcd
$date
	Wed Feb 25 20:35:59 2026
$end
$version
	Icarus Verilog
$end
$timescale
	1ns
$end
$scope module Minority_tb $end
$var wire 1 ! s $end
$var reg 1 " a $end
$var reg 1 # b $end
$var reg 1 $ c $end
$scope module dut $end
$var wire 1 " a $end
$var wire 1 # b $end
$var wire 1 $ c $end
$var wire 1 ! s $end
$var wire 1 % x $end
$var wire 1 & y $end
$var wire 1 ' z $end
$upscope $end
$upscope $end
$enddefinitions $end
#0
$dumpvars
1'
1&
1%
0$
0#
0"
1!
$end
#2
0&
0'
1$
#4
1&
0%
0$
1#
#6
0!
0&
1$
#8
1!
1'
0$
0#
1"
#10
0!
0'
1$
#12
0$
1#
#14
1$
